mcAssistants/__init__.py
mcAssistants/loginHelper.py
mcAssistants/mcHelper.py
mcAssistants/sliceHelper.py
mcAssistants/sqlHelper.py
mcAssistants-1.1.dist-info/METADATA
mcAssistants-1.1.dist-info/WHEEL
mcAssistants-1.1.dist-info/top_level.txt
mcAssistants-1.1.dist-info/RECORD
