Metadata-Version: 2.1
Name: mcAssistants
Version: 1.1
Summary: description
Home-page: UNKNOWN
Author: oujiewen
Author-email: oujiewen2@shoplineapp.com
License: MIT-0
Platform: UNKNOWN
Requires-Python: >=3.5
Requires-Dist: pymysql
